mishikallm_proxy_extras/__init__.py
mishikallm_proxy_extras/_logging.py
mishikallm_proxy_extras/migrations/20250326162113_baseline/migration.sql
mishikallm_proxy_extras/migrations/20250326171002_add_daily_user_table/migration.sql
mishikallm_proxy_extras/migrations/20250327180120_add_api_requests_to_daily_user_table/migration.sql
mishikallm_proxy_extras/migrations/20250329084805_new_cron_job_table/migration.sql
mishikallm_proxy_extras/migrations/20250331215456_track_success_and_failed_requests_daily_agg_table/migration.sql
mishikallm_proxy_extras/migrations/20250411215431_add_managed_file_table/migration.sql
mishikallm_proxy_extras/migrations/20250412081753_team_member_permissions/migration.sql
mishikallm_proxy_extras/migrations/20250415151647_add_cache_read_write_tokens_daily_spend_transactions/migration.sql
mishikallm_proxy_extras/migrations/20250415191926_add_daily_team_table/migration.sql
mishikallm_proxy_extras/migrations/20250416115320_add_tag_table_to_db/migration.sql
mishikallm_proxy_extras/migrations/20250416151339_drop_tag_uniqueness_requirement/migration.sql
mishikallm_proxy_extras/migrations/20250416185146_add_allowed_routes_mishikallm_verification_token/migration.sql
mishikallm_proxy_extras/migrations/20250425182129_add_session_id/migration.sql
mishikallm_proxy_extras/migrations/20250430193429_add_managed_vector_stores/migration.sql
mishikallm_proxy_extras/migrations/migration_lock.toml
mishikallm_proxy_extras/schema.prisma
mishikallm_proxy_extras/utils.py
mishikallm_proxy_extras-0.1.15.dist-info/LICENSE
mishikallm_proxy_extras-0.1.15.dist-info/METADATA
mishikallm_proxy_extras-0.1.15.dist-info/WHEEL
mishikallm_proxy_extras-0.1.15.dist-info/RECORD
